LICENSE
MANIFEST.in
README.rst
setup.py
PIC.egg-info/PKG-INFO
PIC.egg-info/SOURCES.txt
PIC.egg-info/dependency_links.txt
PIC.egg-info/requires.txt
PIC.egg-info/top_level.txt
pic/__init__.py
pic/api/__init__.py
pic/api/poster.py