Metadata-Version: 1.0
Name: PIC
Version: 0.1.0
Summary: 图片合成 API
Home-page: https://github.com/DxqS/PIC
Author: Dxq
Author-email: chk0125@126.com
License: MIT
Keywords: PIL,pillow
Platform: UNKNOWN
